eccodeslib/__init__.py
eccodeslib/bin/bufr_compare
eccodeslib/bin/bufr_compare_dir
eccodeslib/bin/bufr_copy
eccodeslib/bin/bufr_count
eccodeslib/bin/bufr_dump
eccodeslib/bin/bufr_filter
eccodeslib/bin/bufr_get
eccodeslib/bin/bufr_index_build
eccodeslib/bin/bufr_ls
eccodeslib/bin/bufr_set
eccodeslib/bin/codes_bufr_filter
eccodeslib/bin/codes_config
eccodeslib/bin/codes_count
eccodeslib/bin/codes_export_resource
eccodeslib/bin/codes_info
eccodeslib/bin/codes_parser
eccodeslib/bin/codes_split_file
eccodeslib/bin/grib2ppm
eccodeslib/bin/grib_compare
eccodeslib/bin/grib_copy
eccodeslib/bin/grib_count
eccodeslib/bin/grib_dump
eccodeslib/bin/grib_filter
eccodeslib/bin/grib_get
eccodeslib/bin/grib_get_data
eccodeslib/bin/grib_histogram
eccodeslib/bin/grib_index_build
eccodeslib/bin/grib_ls
eccodeslib/bin/grib_set
eccodeslib/bin/gts_compare
eccodeslib/bin/gts_copy
eccodeslib/bin/gts_count
eccodeslib/bin/gts_dump
eccodeslib/bin/gts_filter
eccodeslib/bin/gts_get
eccodeslib/bin/gts_ls
eccodeslib/bin/metar_compare
eccodeslib/bin/metar_copy
eccodeslib/bin/metar_dump
eccodeslib/bin/metar_filter
eccodeslib/bin/metar_get
eccodeslib/bin/metar_ls
eccodeslib/include/eccodes.h
eccodeslib/include/eccodes.mod
eccodeslib/include/eccodes_config.h
eccodeslib/include/eccodes_ecbuild_config.h
eccodeslib/include/eccodes_version.h
eccodeslib/include/eccodes_windef.h
eccodeslib/include/grib_api.h
eccodeslib/include/grib_api.mod
eccodeslib/include/libaec.h
eccodeslib/include/png.h
eccodeslib/include/pngconf.h
eccodeslib/include/pnglibconf.h
eccodeslib/include/szlib.h
eccodeslib/include/libpng16/png.h
eccodeslib/include/libpng16/pngconf.h
eccodeslib/include/libpng16/pnglibconf.h
eccodeslib/include/openjpeg-2.5/openjpeg.h
eccodeslib/include/openjpeg-2.5/opj_config.h
eccodeslib/lib/libaec.0.1.3.dylib
eccodeslib/lib/libaec.0.dylib
eccodeslib/lib/libaec.dylib
eccodeslib/lib/libeccodes.dylib
eccodeslib/lib/libeccodes_f90.dylib
eccodeslib/lib/libeccodes_memfs.dylib
eccodeslib/lib/libopenjp2.2.5.3.dylib
eccodeslib-2.44.0.4.dist-info/licenses/AUTHORS
eccodeslib-2.44.0.4.dist-info/licenses/LICENSE
eccodeslib-2.44.0.4.dist-info/METADATA
eccodeslib-2.44.0.4.dist-info/WHEEL
eccodeslib-2.44.0.4.dist-info/top_level.txt
eccodeslib-2.44.0.4.dist-info/RECORD
