Metadata-Version: 2.4
Name: eccodeslib
Version: 2.44.0.4
Summary: "eccodeslib"
Author: file: AUTHORS
License-File: LICENSE
License-File: AUTHORS
Requires-Dist: eckitlib==1.32.2.4
Requires-Dist: fckitlib==0.14.0.4
Dynamic: license-file
Dynamic: requires-dist
